Workbook

Sheet Invoice
A1: invoice_id | B1: line_id | C1: posted_date | D1: customer_id | E1: customer_segment | F1: sku | G1: quantity | H1: net_revenue_vnd | I1: cogs_vnd | J1: posted_month
A2: INV-202606-B2B-0001 | B2: INV-202606-B2B-0001-L1 | C2: 2026-06-01 | D2: B2B-001 | E2: B2B | F2: PAPER-A4-500 | G2: 8 | H2: 400000 | I2: 320000 | J2: 2026-06
A3: INV-202606-B2B-0001 | B3: INV-202606-B2B-0001-L2 | C3: 2026-06-01 | D3: B2B-001 | E3: B2B | F3: INK-BLACK-100 | G3: 2 | H3: 600000 | I3: 450000 | J3: 2026-06
A4: INV-202606-B2B-0002 | B4: INV-202606-B2B-0002-L1 | C4: 2026-06-01 | D4: B2B-002 | E4: B2B | F4: PAPER-A4-500 | G4: 9 | H4: 450000 | I4: 360000 | J4: 2026-06
A5: INV-202606-B2B-0002 | B5: INV-202606-B2B-0002-L2 | C5: 2026-06-01 | D5: B2B-002 | E5: B2B | F5: INK-BLACK-100 | G5: 2 | H5: 600000 | I5: 450000 | J5: 2026-06
A6: INV-202606-B2B-0003 | B6: INV-202606-B2B-0003-L1 | C6: 2026-06-01 | D6: B2B-003 | E6: B2B | F6: PAPER-A4-500 | G6: 10 | H6: 500000 | I6: 400000 | J6: 2026-06
A7: INV-202606-B2B-0003 | B7: INV-202606-B2B-0003-L2 | C7: 2026-06-01 | D7: B2B-003 | E7: B2B | F7: INK-BLACK-100 | G7: 2 | H7: 600000 | I7: 450000 | J7: 2026-06
A8: INV-202606-B2B-0004 | B8: INV-202606-B2B-0004-L1 | C8: 2026-06-01 | D8: B2B-004 | E8: B2B | F8: PAPER-A4-500 | G8: 11 | H8: 550000 | I8: 440000 | J8: 2026-06
A9: INV-202606-B2B-0004 | B9: INV-202606-B2B-0004-L2 | C9: 2026-06-01 | D9: B2B-004 | E9: B2B | F9: INK-BLACK-100 | G9: 2 | H9: 600000 | I9: 450000 | J9: 2026-06
A10: INV-202606-DIRECT-0001 | B10: INV-202606-DIRECT-0001-L1 | C10: 2026-06-01 | D10: DIRECT-001 | E10: DIRECT | F10: PAPER-A4-500 | G10: 1 | H10: 65000 | I10: 40000 | J10: 2026-06
A11: INV-202606-DIRECT-0001 | B11: INV-202606-DIRECT-0001-L2 | C11: 2026-06-01 | D11: DIRECT-001 | E11: DIRECT | F11: INK-BLACK-100 | G11: 1 | H11: 380000 | I11: 225000 | J11: 2026-06
A12: INV-202606-DIRECT-0002 | B12: INV-202606-DIRECT-0002-L1 | C12: 2026-06-01 | D12: DIRECT-002 | E12: DIRECT | F12: PAPER-A4-500 | G12: 2 | H12: 130000 | I12: 80000 | J12: 2026-06
A13: INV-202606-DIRECT-0002 | B13: INV-202606-DIRECT-0002-L2 | C13: 2026-06-01 | D13: DIRECT-002 | E13: DIRECT | F13: INK-BLACK-100 | G13: 1 | H13: 380000 | I13: 225000 | J13: 2026-06
... A881: INV-202607-DIRECT-0080 | B881: INV-202607-DIRECT-0080-L2 | C881: 2026-07-31 | D881: DIRECT-006 | E881: DIRECT | F881: INK-BLACK-100 | G881: 1 | H881: 380000 | I881: 225000 | J881: 2026-07

Sheet Credit
A1: credit_line_id | B1: posted_date | C1: original_invoice_id | D1: original_line_id | E1: reason_code | F1: returned_quantity | G1: revenue_reduction_vnd | H1: cogs_reversal_vnd | I1: posted_month | J1: segment | K1: sku
A2: CN-2026-0001-L1 | B2: 2026-06-25 | C2: INV-202606-B2B-0001 | D2: INV-202606-B2B-0001-L1 | E2: RETURN_RESELLABLE | F2: 1 | G2: 50000 | H2: 40000 | I2: 2026-06 | J2: B2B | K2: PAPER-A4-500
A3: CN-2026-0007-L1 | B3: 2026-06-25 | C3: INV-202606-B2B-0007 | D3: INV-202606-B2B-0007-L1 | E3: RETURN_RESELLABLE | F3: 1 | G3: 50000 | H3: 40000 | I3: 2026-06 | J3: B2B | K3: PAPER-A4-500
A4: CN-2026-0011-L1 | B4: 2026-06-25 | C4: INV-202606-DIRECT-0001 | D4: INV-202606-DIRECT-0001-L2 | E4: RETURN_RESELLABLE | F4: 1 | G4: 380000 | H4: 225000 | I4: 2026-06 | J4: DIRECT | K4: INK-BLACK-100
A5: CN-2026-0017-L1 | B5: 2026-06-25 | C5: INV-202606-DIRECT-0007 | D5: INV-202606-DIRECT-0007-L2 | E5: RETURN_RESELLABLE | F5: 1 | G5: 380000 | H5: 225000 | I5: 2026-06 | J5: DIRECT | K5: INK-BLACK-100
A6: CN-2026-0002-L1 | B6: 2026-06-26 | C6: INV-202606-B2B-0002 | D6: INV-202606-B2B-0002-L1 | E6: RETURN_RESELLABLE | F6: 1 | G6: 50000 | H6: 40000 | I6: 2026-06 | J6: B2B | K6: PAPER-A4-500
A7: CN-2026-0008-L1 | B7: 2026-06-26 | C7: INV-202606-B2B-0008 | D7: INV-202606-B2B-0008-L1 | E7: RETURN_RESELLABLE | F7: 1 | G7: 50000 | H7: 40000 | I7: 2026-06 | J7: B2B | K7: PAPER-A4-500
A8: CN-2026-0012-L1 | B8: 2026-06-26 | C8: INV-202606-DIRECT-0002 | D8: INV-202606-DIRECT-0002-L2 | E8: RETURN_RESELLABLE | F8: 1 | G8: 380000 | H8: 225000 | I8: 2026-06 | J8: DIRECT | K8: INK-BLACK-100
A9: CN-2026-0018-L1 | B9: 2026-06-26 | C9: INV-202606-DIRECT-0008 | D9: INV-202606-DIRECT-0008-L2 | E9: RETURN_RESELLABLE | F9: 1 | G9: 380000 | H9: 225000 | I9: 2026-06 | J9: DIRECT | K9: INK-BLACK-100
A10: CN-2026-0003-L1 | B10: 2026-06-27 | C10: INV-202606-B2B-0003 | D10: INV-202606-B2B-0003-L1 | E10: RETURN_RESELLABLE | F10: 1 | G10: 50000 | H10: 40000 | I10: 2026-06 | J10: B2B | K10: PAPER-A4-500
A11: CN-2026-0009-L1 | B11: 2026-06-27 | C11: INV-202606-B2B-0009 | D11: INV-202606-B2B-0009-L1 | E11: RETURN_RESELLABLE | F11: 1 | G11: 50000 | H11: 40000 | I11: 2026-06 | J11: B2B | K11: PAPER-A4-500
A12: CN-2026-0013-L1 | B12: 2026-06-27 | C12: INV-202606-DIRECT-0003 | D12: INV-202606-DIRECT-0003-L2 | E12: RETURN_RESELLABLE | F12: 1 | G12: 380000 | H12: 225000 | I12: 2026-06 | J12: DIRECT | K12: INK-BLACK-100
A13: CN-2026-0019-L1 | B13: 2026-06-27 | C13: INV-202606-DIRECT-0009 | D13: INV-202606-DIRECT-0009-L2 | E13: RETURN_RESELLABLE | F13: 1 | G13: 380000 | H13: 225000 | I13: 2026-06 | J13: DIRECT | K13: INK-BLACK-100
... A61: CN-2026-0054-L1 | B61: 2026-07-31 | C61: INV-202607-B2B-0114 | D61: INV-202607-B2B-0114-L2 | E61: SERVICE_ALLOWANCE | F61: 0 | G61: 50000 | H61: 0 | I61: 2026-07 | J61: B2B | K61: INK-BLACK-100

Sheet Carrier
A1: shipment_charge_id | B1: invoice_id | C1: shipped_date | D1: carrier_invoice_date | E1: expense_month | F1: carrier | G1: service | H1: charge_vnd | I1: segment
A2: SHIP-202606-B2B-0001-1 | B2: INV-202606-B2B-0001 | C2: 2026-06-01 | D2: 2026-06-04 | E2: 2026-06 | F2: FleetB2B | G2: STANDARD | H2: 56000 | I2: B2B
A3: SHIP-202606-B2B-0002-1 | B3: INV-202606-B2B-0002 | C3: 2026-06-01 | D3: 2026-06-04 | E3: 2026-06 | F3: FleetB2B | G3: STANDARD | H3: 58000 | I3: B2B
A4: SHIP-202606-B2B-0003-1 | B4: INV-202606-B2B-0003 | C4: 2026-06-01 | D4: 2026-06-04 | E4: 2026-06 | F4: FleetB2B | G4: STANDARD | H4: 36000 | I4: B2B
A5: SHIP-202606-B2B-0003-2 | B5: INV-202606-B2B-0003 | C5: 2026-06-01 | D5: 2026-06-04 | E5: 2026-06 | F5: FleetB2B | G5: STANDARD | H5: 24000 | I5: B2B
A6: SHIP-202606-B2B-0004-1 | B6: INV-202606-B2B-0004 | C6: 2026-06-01 | D6: 2026-06-04 | E6: 2026-06 | F6: FleetB2B | G6: STANDARD | H6: 62000 | I6: B2B
A7: SHIP-202606-DIRECT-0001-1 | B7: INV-202606-DIRECT-0001 | C7: 2026-06-01 | D7: 2026-06-04 | E7: 2026-06 | F7: StandardPost | G7: STANDARD | H7: 26500 | I7: DIRECT
A8: SHIP-202606-DIRECT-0002-1 | B8: INV-202606-DIRECT-0002 | C8: 2026-06-01 | D8: 2026-06-04 | E8: 2026-06 | F8: StandardPost | G8: STANDARD | H8: 27500 | I8: DIRECT
A9: SHIP-202606-DIRECT-0003-1 | B9: INV-202606-DIRECT-0003 | C9: 2026-06-01 | D9: 2026-06-04 | E9: 2026-06 | F9: StandardPost | G9: STANDARD | H9: 28500 | I9: DIRECT
A10: SHIP-202606-DIRECT-0004-1 | B10: INV-202606-DIRECT-0004 | C10: 2026-06-01 | D10: 2026-06-04 | E10: 2026-06 | F10: StandardPost | G10: STANDARD | H10: 29500 | I10: DIRECT
A11: SHIP-202606-B2B-0005-1 | B11: INV-202606-B2B-0005 | C11: 2026-06-02 | D11: 2026-06-05 | E11: 2026-06 | F11: FleetB2B | G11: STANDARD | H11: 64000 | I11: B2B
A12: SHIP-202606-B2B-0006-1 | B12: INV-202606-B2B-0006 | C12: 2026-06-02 | D12: 2026-06-05 | E12: 2026-06 | F12: FleetB2B | G12: STANDARD | H12: 33600 | I12: B2B
A13: SHIP-202606-B2B-0006-2 | B13: INV-202606-B2B-0006 | C13: 2026-06-02 | D13: 2026-06-05 | E13: 2026-06 | F13: FleetB2B | G13: STANDARD | H13: 22400 | I13: B2B
... A527: SHIP-202607-DIRECT-0080-1 | B527: INV-202607-DIRECT-0080 | C527: 2026-07-31 | D527: 2026-08-03 | E527: 2026-07 | F527: StandardPost | G527: STANDARD | H527: 22000 | I527: DIRECT

Sheet Finance
A1: accounting_month | B1: net_sales_vnd | C1: net_cogs_vnd | D1: outbound_freight_vnd | E1: close_status
A2: 2026-06 | B2: 156700000 | C2: 112850000 | D2: 8850000 | E2: CLOSED
A3: 2026-07 | B3: 200800000 | C3: 154150000 | D3: 15700000 | E3: CLOSED

Sheet Summary
A1: Minh An Office - giả lập, VND nguyên đồng
A3: Tháng | B3: DT hóa đơn | C3: Credit theo ngày ghi sổ | D3: Doanh thu thuần | E3: GV hóa đơn | F3: Hoàn GV | G3: Giá vốn thuần | H3: Lãi gộp | I3: Cước kết nối | J3: Cước toàn công ty | K3: Cước chưa gán nhóm | L3: Đóng góp chính thức | M3: Tỷ suất | N3: Sai lệch DT | O3: Sai lệch GV
A4: 2026-06 | B4: =SUMIF(Invoice!J:J,A4,Invoice!H:H) -> 161000000 | C4: =SUMIF(Credit!I:I,A4,Credit!G:G) -> 4300000 | D4: =B4-C4 -> 156700000 | E4: =SUMIF(Invoice!J:J,A4,Invoice!I:I) -> 115500000 | F4: =SUMIF(Credit!I:I,A4,Credit!H:H) -> 2650000 | G4: =E4-F4 -> 112850000 | H4: =D4-G4 -> 43850000 | I4: =SUMIF(Carrier!E:E,A4,Carrier!H:H) -> 8850000 | J4: =Finance!D2 -> 8850000 | K4: =J4-I4 -> 0 | L4: =H4-J4 -> 35000000 | M4: =L4/D4 -> 0.22335673 | N4: =D4-Finance!B2 -> 0 | O4: =G4-Finance!C2 -> 0
A5: 2026-07 | B5: =SUMIF(Invoice!J:J,A5,Invoice!H:H) -> 210400000 | C5: =SUMIF(Credit!I:I,A5,Credit!G:G) -> 9600000 | D5: =B5-C5 -> 200800000 | E5: =SUMIF(Invoice!J:J,A5,Invoice!I:I) -> 160400000 | F5: =SUMIF(Credit!I:I,A5,Credit!H:H) -> 6250000 | G5: =E5-F5 -> 154150000 | H5: =D5-G5 -> 46650000 | I5: =SUMIF(Carrier!E:E,A5,Carrier!H:H) -> 12700000 | J5: =Finance!D3 -> 15700000 | K5: =J5-I5 -> 3000000 | L5: =H5-J5 -> 30950000 | M5: =L5/D5 -> 0.15413347 | N5: =D5-Finance!B3 -> 0 | O5: =G5-Finance!C3 -> 0
A8: Tổng số: Finance khóa sổ. Credit dùng tháng ghi sổ; cước dùng expense_month. Cước thiếu không chia tỷ lệ doanh thu.

Sheet Segments
A1: Tháng | B1: Nhóm | C1: Số hóa đơn | D1: DT thuần | E1: GV thuần | F1: Lãi gộp | G1: Cước kết nối | H1: Đóng góp SAU CƯỚC KẾT NỐI
A2: 2026-06 | B2: B2B | C2: 100 | D2: =SUMIFS(Invoice!H:H,Invoice!J:J,A2,Invoice!E:E,B2)-SUMIFS(Credit!G:G,Credit!I:I,A2,Credit!J:J,B2) -> 109500000 | E2: =SUMIFS(Invoice!I:I,Invoice!J:J,A2,Invoice!E:E,B2)-SUMIFS(Credit!H:H,Credit!I:I,A2,Credit!J:J,B2) -> 84600000 | F2: =D2-E2 -> 24900000 | G2: =SUMIFS(Carrier!H:H,Carrier!E:E,A2,Carrier!I:I,B2) -> 6000000 | H2: =F2-G2 -> 18900000
A3: 2026-06 | B3: DIRECT | C3: 100 | D3: =SUMIFS(Invoice!H:H,Invoice!J:J,A3,Invoice!E:E,B3)-SUMIFS(Credit!G:G,Credit!I:I,A3,Credit!J:J,B3) -> 47200000 | E3: =SUMIFS(Invoice!I:I,Invoice!J:J,A3,Invoice!E:E,B3)-SUMIFS(Credit!H:H,Credit!I:I,A3,Credit!J:J,B3) -> 28250000 | F3: =D3-E3 -> 18950000 | G3: =SUMIFS(Carrier!H:H,Carrier!E:E,A3,Carrier!I:I,B3) -> 2850000 | H3: =F3-G3 -> 16100000
A4: 2026-07 | B4: B2B | C4: 160 | D4: =SUMIFS(Invoice!H:H,Invoice!J:J,A4,Invoice!E:E,B4)-SUMIFS(Credit!G:G,Credit!I:I,A4,Credit!J:J,B4) -> 163800000 | E4: =SUMIFS(Invoice!I:I,Invoice!J:J,A4,Invoice!E:E,B4)-SUMIFS(Credit!H:H,Credit!I:I,A4,Credit!J:J,B4) -> 132000000 | F4: =D4-E4 -> 31800000 | G4: =SUMIFS(Carrier!H:H,Carrier!E:E,A4,Carrier!I:I,B4) -> 11100000 | H4: =F4-G4 -> 20700000
A5: 2026-07 | B5: DIRECT | C5: 80 | D5: =SUMIFS(Invoice!H:H,Invoice!J:J,A5,Invoice!E:E,B5)-SUMIFS(Credit!G:G,Credit!I:I,A5,Credit!J:J,B5) -> 37000000 | E5: =SUMIFS(Invoice!I:I,Invoice!J:J,A5,Invoice!E:E,B5)-SUMIFS(Credit!H:H,Credit!I:I,A5,Credit!J:J,B5) -> 22150000 | F5: =D5-E5 -> 14850000 | G5: =SUMIFS(Carrier!H:H,Carrier!E:E,A5,Carrier!I:I,B5) -> 1600000 | H5: =F5-G5 -> 13250000

Sheet Price
A1: Tháng | B1: Nhóm | C1: SKU | D1: SL hóa đơn | E1: DT hóa đơn | F1: Giá thực thu/đơn vị, trước credit
A2: 2026-06 | B2: B2B | C2: INK-BLACK-100 | D2: =SUMIFS(Invoice!G:G,Invoice!J:J,A2,Invoice!E:E,B2,Invoice!F:F,C2) -> 200 | E2: =SUMIFS(Invoice!H:H,Invoice!J:J,A2,Invoice!E:E,B2,Invoice!F:F,C2) -> 60000000 | F2: =E2/D2 -> 300000
A3: 2026-06 | B3: B2B | C3: PAPER-A4-500 | D3: =SUMIFS(Invoice!G:G,Invoice!J:J,A3,Invoice!E:E,B3,Invoice!F:F,C3) -> 1000 | E3: =SUMIFS(Invoice!H:H,Invoice!J:J,A3,Invoice!E:E,B3,Invoice!F:F,C3) -> 50000000 | F3: =E3/D3 -> 50000
A4: 2026-06 | B4: DIRECT | C4: INK-BLACK-100 | D4: =SUMIFS(Invoice!G:G,Invoice!J:J,A4,Invoice!E:E,B4,Invoice!F:F,C4) -> 100 | E4: =SUMIFS(Invoice!H:H,Invoice!J:J,A4,Invoice!E:E,B4,Invoice!F:F,C4) -> 38000000 | F4: =E4/D4 -> 380000
A5: 2026-06 | B5: DIRECT | C5: PAPER-A4-500 | D5: =SUMIFS(Invoice!G:G,Invoice!J:J,A5,Invoice!E:E,B5,Invoice!F:F,C5) -> 200 | E5: =SUMIFS(Invoice!H:H,Invoice!J:J,A5,Invoice!E:E,B5,Invoice!F:F,C5) -> 13000000 | F5: =E5/D5 -> 65000
A6: 2026-07 | B6: B2B | C6: INK-BLACK-100 | D6: =SUMIFS(Invoice!G:G,Invoice!J:J,A6,Invoice!E:E,B6,Invoice!F:F,C6) -> 320 | E6: =SUMIFS(Invoice!H:H,Invoice!J:J,A6,Invoice!E:E,B6,Invoice!F:F,C6) -> 92800000 | F6: =E6/D6 -> 290000
A7: 2026-07 | B7: B2B | C7: PAPER-A4-500 | D7: =SUMIFS(Invoice!G:G,Invoice!J:J,A7,Invoice!E:E,B7,Invoice!F:F,C7) -> 1600 | E7: =SUMIFS(Invoice!H:H,Invoice!J:J,A7,Invoice!E:E,B7,Invoice!F:F,C7) -> 76800000 | F7: =E7/D7 -> 48000
A8: 2026-07 | B8: DIRECT | C8: INK-BLACK-100 | D8: =SUMIFS(Invoice!G:G,Invoice!J:J,A8,Invoice!E:E,B8,Invoice!F:F,C8) -> 80 | E8: =SUMIFS(Invoice!H:H,Invoice!J:J,A8,Invoice!E:E,B8,Invoice!F:F,C8) -> 30400000 | F8: =E8/D8 -> 380000
A9: 2026-07 | B9: DIRECT | C9: PAPER-A4-500 | D9: =SUMIFS(Invoice!G:G,Invoice!J:J,A9,Invoice!E:E,B9,Invoice!F:F,C9) -> 160 | E9: =SUMIFS(Invoice!H:H,Invoice!J:J,A9,Invoice!E:E,B9,Invoice!F:F,C9) -> 10400000 | F9: =E9/D9 -> 65000

Sheet Definitions
A1: Mục | B1: Định nghĩa / SHA256
A2: status | B2: All names and data synthetic; proposal not approved or executed.
A3: snapshot | B3: 2026-08-07; Vietnam time; June and July 2026 closed accounting periods.
A4: currency | B4: Whole VND, excluding VAT. Display in million VND where explicitly labeled.
A5: authority | B5: monthly_finance.csv governs whole-company monthly KPI; invoice and credit postings reconcile sales/COGS; connected carrier export covers only two carriers.
A6: grain | B6: Invoice line is unique by line_id; credits by credit_line_id; charges by shipment_charge_id. Aggregate each additive source before joining totals.
A7: contribution | B7: net_sales - net_cogs - outbound_freight; not net company profit; excludes overhead.
A8: credits | B8: Use credit posted month for monthly P&L; original line supplies segment only. July includes credits on June invoices.
A9: freight | B9: Use expense_month, not carrier_invoice_date or invoice posted month.
A10: segment_contribution | B10: Gross profit minus connected freight ONLY; unconnected freight is not assigned by an invented rule.
A11: price | B11: Invoice realized revenue / invoice quantity, before later credits; no list price or discount rule in the input.
A12: causality | B12: Descriptive comparison, no causal intervention effect or recoverable savings established.
... A17: source-notes.md | B17: 783003e731b21246c3a8e81cc54173941a6f4475455c276e9248499775b60fbd

Sheet Decision_log
A1: record_id | B1: synthetic | C1: question | D1: evidence_snapshot | E1: proposal | F1: evidence_completed | G1: decision_owner_proposed | H1: metric_steward_proposed | I1: executor_proposed | J1: approval_state | K1: actual_decision | L1: execution_state | M1: eligible_scope | N1: window | O1: comparison | P1: outcome | Q1: guardrails | R1: mature_readout | S1: observed_result | T1: decision_rule_proposed | U1: next_step | V1: reader_understanding
A2: SYN-ANALYSIS-01 | B2: TRUE | C2: Vì sao doanh thu tháng 7 tăng nhưng đóng góp giảm? | D2: 07/08/2026; 5 nguồn; SHA256 trong analysis.json | E2: Thử thay đổi giao hàng có giới hạn; đối soát 3 triệu chưa gán nhóm | F2: Đã đối soát sales/COGS, tính bridge +2,80 -6,85 = -4,05 triệu | G2: Chủ doanh nghiệp | H2: Kế toán | I2: Phụ trách giao hàng | J2: CHUA_PHE_DUYET | K2: CHUA_QUAN_SAT | L2: CHUA_THUC_HIEN | M2: Tối đa 20 tài khoản / 60 yêu cầu B2B; SLA cho phép STANDARD | N2: 4 tuần từ T0 chưa ấn định; dừng nhận T0+27 | O2: Phân nhóm theo cặp tài khoản; STANDARD vs hiện trạng | P2: Đóng góp/yêu cầu sau mọi credit, cước và chi phí tăng thêm | Q2: 1 triệu chi phí tăng thêm; dừng khi trễ cam kết do thay đổi; 2h/tuần/vai trò | R2: Muộn hơn: yêu cầu cuối +14 ngày và kế toán xác nhận đủ cước/credit; chưa biết ngày | S2: CHUA_QUAN_SAT | T2: >=5.000 VND/yêu cầu, đủ nguồn, không hại SLA/nhu cầu; chỉ tiếp tục nhỏ | U2: Chủ DN chốt người/trần; kế toán phân bổ 3 triệu; vận hành xác minh cam kết | V2: CHUA_CO_PHAN_HOI_NGUOI_DOC
A3: SYN-DATA-02 | B3: TRUE | C3: Cước ngoài kết nối tháng 7 thuộc nhóm/hoạt động nào? | D3: Finance 15,70 triệu - carrier export 12,70 triệu | E3: Lấy hóa đơn hãng ngoài kết nối, liên kết đơn và lý do giao lại | F3: Đã tính chênh lệch 3.000.000 VND; chưa có nguồn để phân bổ | G3: Chủ doanh nghiệp | H3: Kế toán | I3: Kế toán | J3: CHUA_PHE_DUYET | K3: CHUA_QUAN_SAT | L3: CHUA_THUC_HIEN | M3: Toàn bộ cước giao ra tháng dịch vụ 7/2026 | N3: Trước T0; ngày chưa ấn định | O3: Đối soát với tổng khóa sổ, tolerance 0 VND hoặc giải thích riêng | P3: Số tiền gán được nhóm và cước chưa gán | Q3: Không chia tỷ lệ doanh thu để giả tạo số chính xác | R3: Khi kế toán xác nhận nguồn đủ; chưa có ngày | S3: CHUA_QUAN_SAT | T3: Nếu nguyên nhân ưu tiên khác EXPRESS thì xét lại phạm vi trước mở thử | U3: Kế toán yêu cầu nguồn nội bộ sau khi chủ DN phê duyệt | V3: CHUA_CO_PHAN_HOI_NGUOI_DOC
